{
  "version": 2,
  "nodes": {
    "file:///Users/jpravetz/dev/@epdoc/strava/packages/gpx/src/mod.ts": {
      "symbols": [
        {
          "name": "GpxCommand",
          "declarations": [
            {
              "location": {
                "filename": "file:///Users/jpravetz/dev/@epdoc/strava/packages/gpx/src/cmd.ts",
                "line": 31,
                "col": 0,
                "byteIndex": 956
              },
              "declarationKind": "export",
              "kind": "class",
              "def": {
                "methods": [
                  {
                    "isOverride": true,
                    "name": "defineMetadata",
                    "kind": "method",
                    "functionDef": {
                      "params": [],
                      "returnType": {
                        "repr": "void",
                        "kind": "keyword",
                        "value": "void"
                      },
                      "hasBody": true
                    },
                    "location": {
                      "filename": "file:///Users/jpravetz/dev/@epdoc/strava/packages/gpx/src/cmd.ts",
                      "line": 32,
                      "col": 2,
                      "byteIndex": 1024
                    }
                  },
                  {
                    "isOverride": true,
                    "name": "defineOptions",
                    "kind": "method",
                    "functionDef": {
                      "params": [],
                      "returnType": {
                        "repr": "void",
                        "kind": "keyword",
                        "value": "void"
                      },
                      "hasBody": true
                    },
                    "location": {
                      "filename": "file:///Users/jpravetz/dev/@epdoc/strava/packages/gpx/src/cmd.ts",
                      "line": 37,
                      "col": 2,
                      "byteIndex": 1150
                    }
                  },
                  {
                    "isOverride": true,
                    "name": "execute",
                    "kind": "method",
                    "functionDef": {
                      "params": [
                        {
                          "kind": "identifier",
                          "name": "options",
                          "optional": false,
                          "tsType": {
                            "repr": "GpxCmdOptions",
                            "kind": "typeRef",
                            "value": {
                              "typeName": "GpxCmdOptions",
                              "resolution": {
                                "kind": "local"
                              }
                            }
                          }
                        },
                        {
                          "kind": "identifier",
                          "name": "_args",
                          "optional": false,
                          "tsType": {
                            "repr": "CliApp.CmdArgs",
                            "kind": "typeRef",
                            "value": {
                              "typeName": "CliApp.CmdArgs",
                              "resolution": {
                                "kind": "import",
                                "specifier": "@epdoc/cliapp"
                              }
                            }
                          }
                        }
                      ],
                      "returnType": {
                        "repr": "Promise",
                        "kind": "typeRef",
                        "value": {
                          "typeParams": [
                            {
                              "repr": "void",
                              "kind": "keyword",
                              "value": "void"
                            }
                          ],
                          "typeName": "Promise"
                        }
                      },
                      "hasBody": true,
                      "isAsync": true
                    },
                    "location": {
                      "filename": "file:///Users/jpravetz/dev/@epdoc/strava/packages/gpx/src/cmd.ts",
                      "line": 53,
                      "col": 2,
                      "byteIndex": 1898
                    }
                  },
                  {
                    "name": "helpText",
                    "kind": "method",
                    "functionDef": {
                      "params": [],
                      "returnType": {
                        "repr": "string",
                        "kind": "keyword",
                        "value": "string"
                      },
                      "hasBody": true
                    },
                    "location": {
                      "filename": "file:///Users/jpravetz/dev/@epdoc/strava/packages/gpx/src/cmd.ts",
                      "line": 130,
                      "col": 2,
                      "byteIndex": 4581
                    }
                  }
                ],
                "extends": "BaseRootCmdClass",
                "superTypeParams": [
                  {
                    "repr": "GpxCmdOptions",
                    "kind": "typeRef",
                    "value": {
                      "typeName": "GpxCmdOptions",
                      "resolution": {
                        "kind": "local"
                      }
                    }
                  }
                ]
              }
            }
          ]
        }
      ]
    }
  }
}
